standardmodelbio/__init__.py
standardmodelbio-0.0.0.dist-info/METADATA
standardmodelbio-0.0.0.dist-info/WHEEL
standardmodelbio-0.0.0.dist-info/RECORD
